polugins_type_gen/__init__.py
polugins_type_gen/__main__.py
polugins_type_gen/_ast.py
polugins_type_gen/_version.py
polugins_type_gen/cli.py
polugins_type_gen/_testing/namespaces.py
polugins_type_gen-0.6.1.dist-info/METADATA
polugins_type_gen-0.6.1.dist-info/WHEEL
polugins_type_gen-0.6.1.dist-info/entry_points.txt
polugins_type_gen-0.6.1.dist-info/RECORD
