Metadata-Version: 2.4
Name: polugins_type_gen
Version: 0.6.1
Summary: Type stub generator Polugins.
Author-email: StefanBRas <opensource@bruhn.io>
Requires-Python: <4.0.0,>=3.9.0
Requires-Dist: polugins>=0.2
